OmniSlicer/OmniSlicer.py
OmniSlicer/__init__.py
omnislicer-0.0.8.dist-info/licenses/LICENSE
omnislicer-0.0.8.dist-info/METADATA
omnislicer-0.0.8.dist-info/WHEEL
omnislicer-0.0.8.dist-info/top_level.txt
omnislicer-0.0.8.dist-info/RECORD
