Metadata-Version: 2.4
Name: OmniSlicer
Version: 0.0.8
Summary: Omnidirectional Volume Slicing Package for 3D Medical Image Analysis
Author-email: Johannes Kiechle <johannes.kiechle@tum.de>
License-Expression: MIT
Project-URL: Homepage, https://github.com/hannesk95/OmniSlicer
Classifier: Programming Language :: Python :: 3
Classifier: Operating System :: OS Independent
Requires-Python: >=3.9
License-File: LICENSE
Requires-Dist: torch>=2.6.0
Requires-Dist: trimesh>=4.6.8
Requires-Dist: numpy>=2.2.6
Requires-Dist: pyvista>=0.45.0
Requires-Dist: torchio>=0.20.7
Requires-Dist: tqdm>=4.67.1
Requires-Dist: torchvision>=0.21.0
Dynamic: license-file
